microenv/__init__.py
microenv/microenv.py
microenv-0.1.1.dist-info/METADATA
microenv-0.1.1.dist-info/WHEEL
microenv-0.1.1.dist-info/licenses/LICENSE
microenv-0.1.1.dist-info/RECORD
