Metadata-Version: 2.4
Name: microenv
Version: 0.1.1
Summary: Functional dependency paradigm
Project-URL: Homepage, https://github.com/ceil-python/microenv
Author-email: Sergey Shkatula <sergey@ceil.dev>
License-Expression: MIT
License-File: LICENSE
Keywords: env,environment,micro,microenv
Requires-Python: >=3.7
